README.txt
setup.py
example_pkg_pixelstudios.egg-info/PKG-INFO
example_pkg_pixelstudios.egg-info/SOURCES.txt
example_pkg_pixelstudios.egg-info/dependency_links.txt
example_pkg_pixelstudios.egg-info/top_level.txt
pixelpricecal/__init__.py
pixelpricecal/pixel_properties.py